patta/__init__.py
patta/__version__.py
patta/aliases.py
patta/base.py
patta/dataloader.py
patta/functional.py
patta/load_model.py
patta/transforms.py
patta/wrappers.py
patta-0.0.2.dist-info/LICENSE
patta-0.0.2.dist-info/METADATA
patta-0.0.2.dist-info/WHEEL
patta-0.0.2.dist-info/top_level.txt
patta-0.0.2.dist-info/RECORD
