Metadata-Version: 2.1
Name: patta
Version: 0.0.2
Summary: Images test time augmentation with Paddle.
Home-page: UNKNOWN
License: MIT
Platform: UNKNOWN
Classifier: License :: OSI Approved :: MIT License
Classifier: Programming Language :: Python
Classifier: Programming Language :: Python :: 3
Classifier: Programming Language :: Python :: Implementation :: CPython
Classifier: Programming Language :: Python :: Implementation :: PyPy
Requires-Python: >=3.0.0
Provides-Extra: test
Requires-Dist: pytest ; extra == 'test'
